nepali_citizen_transliterator/__init__.py
nepali_citizen_transliterator/patterns.py
nepali_citizen_transliterator/transliterator.py
nepali_citizen_transliterator-1.0.2.dist-info/LICENSE
nepali_citizen_transliterator-1.0.2.dist-info/METADATA
nepali_citizen_transliterator-1.0.2.dist-info/WHEEL
nepali_citizen_transliterator-1.0.2.dist-info/top_level.txt
nepali_citizen_transliterator-1.0.2.dist-info/RECORD
