Metadata-Version: 2.1
Name: nepali-citizen-transliterator
Version: 1.0.2
Summary: Convert Romanized Nepali names/addresses to Devanagari script
Home-page: https://github.com/manjil-budhathoki/nepali-citizen-transliterator
Author: theFoolishOne
Author-email: theFoolishOne <manjilbbudhathoki@gmail.com>
License: MIT
Keywords: nepali,devanagari,transliteration,citizen
Classifier: Programming Language :: Python :: 3
Classifier: License :: OSI Approved :: MIT License
Classifier: Operating System :: OS Independent
Requires-Python: >=3.6
License-File: LICENSE
